invoicing/__init__.py
invoicing/admin.py
invoicing/apps.py
invoicing/exporters.py
invoicing/helpers.py
invoicing/managers.py
invoicing/models.py
invoicing/querysets.py
invoicing/settings.py
invoicing/signals.py
invoicing/urls.py
invoicing/utils.py
invoicing/views.py
invoicing/formatters/__init__.py
invoicing/formatters/html.py
invoicing/formatters/pdf.py
invoicing/locale/cs/LC_MESSAGES/django.mo
invoicing/locale/cs/LC_MESSAGES/django.po
invoicing/locale/de/LC_MESSAGES/django.mo
invoicing/locale/de/LC_MESSAGES/django.po
invoicing/locale/hu/LC_MESSAGES/django.mo
invoicing/locale/hu/LC_MESSAGES/django.po
invoicing/locale/pl/LC_MESSAGES/django.mo
invoicing/locale/pl/LC_MESSAGES/django.po
invoicing/locale/ro/LC_MESSAGES/django.mo
invoicing/locale/ro/LC_MESSAGES/django.po
invoicing/locale/sk/LC_MESSAGES/django.mo
invoicing/locale/sk/LC_MESSAGES/django.po
invoicing/migrations/0001_initial.py
invoicing/migrations/0002_auto_20170123_1806.py
invoicing/migrations/0003_auto_20170123_1810.py
invoicing/migrations/0004_auto_20170522_1207.py
invoicing/migrations/0005_auto_20171026_0009.py
invoicing/migrations/0006_auto_20180529_1224.py
invoicing/migrations/0007_auto_20180529_1601.py
invoicing/migrations/0008_recalculate.py
invoicing/migrations/0009_auto_20180531_1816.py
invoicing/migrations/0010_recalculate_vat.py
invoicing/migrations/0011_auto_20180601_1459.py
invoicing/migrations/0012_rename_number_to_sequence.py
invoicing/migrations/0013_rename_full_number_to_number.py
invoicing/migrations/0014_recalculate.py
invoicing/migrations/0015_auto_20180605_1232.py
invoicing/migrations/0016_update_credit_notes.py
invoicing/migrations/0017_auto_20180619_1349.py
invoicing/migrations/0018_invoice_attachments.py
invoicing/migrations/0019_recalculate.py
invoicing/migrations/0020_auto_20181001_1025.py
invoicing/migrations/0021_invoice_related_document.py
invoicing/migrations/0022_invoice_date_paid.py
invoicing/migrations/0023_invoice_related_invoices.py
django_invoicing-9.0.1.dist-info/LICENSE
django_invoicing-9.0.1.dist-info/METADATA
django_invoicing-9.0.1.dist-info/WHEEL
django_invoicing-9.0.1.dist-info/top_level.txt
django_invoicing-9.0.1.dist-info/RECORD
