Metadata-Version: 2.1
Name: django-invoicing
Version: 9.0.1
Summary: Django app for invoicing.
Home-page: https://github.com/PragmaticMates/django-invoicing
Author: Pragmatic Mates
Author-email: info@pragmaticmates.com
Maintainer: Pragmatic Mates
Maintainer-email: info@pragmaticmates.com
License: GPL License
Keywords: django invoice invoicing billing supplier issuer purchaser buyer commerce products taxes vat pdf
Classifier: Programming Language :: Python
Classifier: Programming Language :: Python :: 3.5
Classifier: Operating System :: OS Independent
Classifier: Environment :: Web Environment
Classifier: Intended Audience :: Developers
Classifier: Framework :: Django
Classifier: License :: OSI Approved :: BSD License
Classifier: Development Status :: 3 - Alpha
License-File: LICENSE
Requires-Dist: django>=4.2
Requires-Dist: django-countries
Requires-Dist: django-model-utils
Requires-Dist: django-money
Requires-Dist: django-localflavor
Requires-Dist: django-internationalflavor
